voiceeval/__init__.py
voiceeval/client.py
voiceeval/models.py
voiceeval/audio/__init__.py
voiceeval/audio/ingestion.py
voiceeval/audio/transcription.py
voiceeval/audio/vad.py
voiceeval/metrics/__init__.py
voiceeval/metrics/base.py
voiceeval/metrics/conversation.py
voiceeval/metrics/performance.py
voiceeval/metrics/voice.py
voiceeval/observability/__init__.py
voiceeval/observability/instrumentation.py
voiceeval/runners/__init__.py
voiceeval/runners/offline.py
voiceeval/runners/simulator.py
voiceeval_sdk-0.1.1.dist-info/METADATA
voiceeval_sdk-0.1.1.dist-info/WHEEL
voiceeval_sdk-0.1.1.dist-info/licenses/LICENSE
voiceeval_sdk-0.1.1.dist-info/RECORD
