Metadata-Version: 2.4
Name: voiceeval-sdk
Version: 0.1.1
Summary: Enterprise-grade Observability and Evaluation SDK for Voice Agents
Project-URL: Repository, https://github.com/voiceeval/voiceeval-sdk
Project-URL: Homepage, https://voiceeval.com
Author-email: VoiceEval Team <hello@voiceeval.com>
License: MIT License
License-File: LICENSE
Classifier: Development Status :: 4 - Beta
Classifier: Intended Audience :: Developers
Classifier: License :: OSI Approved :: MIT License
Classifier: Programming Language :: Python :: 3.11
Classifier: Topic :: Software Development :: Libraries :: Python Modules
Requires-Python: >=3.11
Requires-Dist: fastapi>=0.127.1
Requires-Dist: httpx>=0.28.1
Requires-Dist: openai>=2.14.0
Requires-Dist: opentelemetry-api>=1.39.1
Requires-Dist: opentelemetry-exporter-otlp>=1.39.1
Requires-Dist: opentelemetry-instrumentation-anthropic>=0.50.1
Requires-Dist: opentelemetry-instrumentation-google-generativeai>=0.50.1
Requires-Dist: opentelemetry-instrumentation-openai>=0.50.1
Requires-Dist: opentelemetry-sdk>=1.39.1
Requires-Dist: pydantic>=2.0.0
Requires-Dist: python-dotenv>=1.2.1
Requires-Dist: uvicorn>=0.40.0
